numberutilities/__init__.py
numberutilities-2.0.dist-info/LICENSE
numberutilities-2.0.dist-info/METADATA
numberutilities-2.0.dist-info/WHEEL
numberutilities-2.0.dist-info/top_level.txt
numberutilities-2.0.dist-info/RECORD
