Metadata-Version: 2.1
Name: numberutilities
Version: 2.0
Summary: A tool to know if a numer is prime.
Home-page: UNKNOWN
Author: Cristina Galván
Author-email: cristina.galvan.prieto@hotmail.com
License: GNU GPLv3
Keywords: prime mathematical operations
Platform: UNKNOWN
Classifier: Development Status :: 4 - Beta
Classifier: Intended Audience :: Developers
Classifier: Topic :: Utilities
Classifier: License :: OSI Approved :: GNU General Public License v3 (GPLv3)
Classifier: Programming Language :: Python :: 3
Classifier: Operating System :: OS Independent
